stepperpi/__init__.py
stepperpi/stepper.py
stepperpi-0.0.1.dist-info/LICENSE
stepperpi-0.0.1.dist-info/METADATA
stepperpi-0.0.1.dist-info/WHEEL
stepperpi-0.0.1.dist-info/entry_points.txt
stepperpi-0.0.1.dist-info/top_level.txt
stepperpi-0.0.1.dist-info/RECORD
